{
  "name": "Makinda Dark",
  "background": "#0e0e0f",
  "foreground": "#e4e4e7",
  "cursorColor": "#ff711a",
  "selectionBackground": "#27272a",
  "black": "#0e0e0f",
  "red": "#fb7185",
  "green": "#34d399",
  "yellow": "#fbbf24",
  "blue": "#60a5fa",
  "purple": "#a26ee2",
  "cyan": "#2dd4bf",
  "white": "#e4e4e7",
  "brightBlack": "#71717a",
  "brightRed": "#fda4af",
  "brightGreen": "#6ee7b7",
  "brightYellow": "#fde68a",
  "brightBlue": "#93c5fd",
  "brightPurple": "#c1a5e4",
  "brightCyan": "#67e8f9",
  "brightWhite": "#ffffff"
}
